basekk/__init__.py
basekk/hello_test.py
basekk-0.0.0.1.dist-info/METADATA
basekk-0.0.0.1.dist-info/WHEEL
basekk-0.0.0.1.dist-info/top_level.txt
basekk-0.0.0.1.dist-info/RECORD
