Metadata-Version: 2.1
Name: basekk
Version: 0.0.0.1
Summary: hello world 테스트.
Home-page: 
Author: basekk
Author-email: jino152637@gmail.com
License: MIT
Requires-Python: >=3.4
